PhpKaifazheShijian/README.md
PhpKaifazheShijian/__init__.py
PhpKaifazheShijian/__main__.py
PhpKaifazheShijian/file.epub
PhpKaifazheShijian/index.html
PhpKaifazheShijian/css/__init__.py
PhpKaifazheShijian/css/annotations.css
PhpKaifazheShijian/css/main.css
PhpKaifazheShijian/css/normalize.css
PhpKaifazheShijian/css/popup.css
PhpKaifazheShijian/font/__init__.py
PhpKaifazheShijian/font/fontello.eot
PhpKaifazheShijian/font/fontello.svg
PhpKaifazheShijian/font/fontello.ttf
PhpKaifazheShijian/font/fontello.woff
PhpKaifazheShijian/img/__init__.py
PhpKaifazheShijian/img/annotator-glyph-sprite.png
PhpKaifazheShijian/img/annotator-icon-sprite.png
PhpKaifazheShijian/img/apple-touch-icon.png
PhpKaifazheShijian/img/cancelfullscreen.png
PhpKaifazheShijian/img/close.png
PhpKaifazheShijian/img/fullscreen.png
PhpKaifazheShijian/img/loader.gif
PhpKaifazheShijian/img/menu-icon.png
PhpKaifazheShijian/img/save.png
PhpKaifazheShijian/img/saved.png
PhpKaifazheShijian/img/settings-s.png
PhpKaifazheShijian/img/settings.png
PhpKaifazheShijian/img/star.png
PhpKaifazheShijian/js/__init__.py
PhpKaifazheShijian/js/epub.js
PhpKaifazheShijian/js/epub.min.js
PhpKaifazheShijian/js/epub.min.map
PhpKaifazheShijian/js/hooks.min.js
PhpKaifazheShijian/js/hooks.min.map
PhpKaifazheShijian/js/reader.js
PhpKaifazheShijian/js/reader.js.map
PhpKaifazheShijian/js/reader.min.js
PhpKaifazheShijian/js/reader.min.map
PhpKaifazheShijian/js/hooks/__init__.py
PhpKaifazheShijian/js/hooks/extensions/__init__.py
PhpKaifazheShijian/js/hooks/extensions/highlight.js
PhpKaifazheShijian/js/libs/__init__.py
PhpKaifazheShijian/js/libs/jquery.min.js
PhpKaifazheShijian/js/libs/localforage.min.js
PhpKaifazheShijian/js/libs/screenfull.js
PhpKaifazheShijian/js/libs/screenfull.min.js
PhpKaifazheShijian/js/libs/zip.min.js
PhpKaifazheShijian/js/plugins/__init__.py
PhpKaifazheShijian/js/plugins/hypothesis.js
PhpKaifazheShijian/js/plugins/search.js
php_kaifazhe_shijian-2024.3.2.0.dist-info/METADATA
php_kaifazhe_shijian-2024.3.2.0.dist-info/WHEEL
php_kaifazhe_shijian-2024.3.2.0.dist-info/entry_points.txt
php_kaifazhe_shijian-2024.3.2.0.dist-info/top_level.txt
php_kaifazhe_shijian-2024.3.2.0.dist-info/RECORD
